<?xml version="1.0" encoding="UTF-8"?>
<votingplace vp_id="2980" vp_e_no="4" e_no="4" vp_no="25" updated="2024-11-10T00:00:00">
    <time_received>2023-10-27T11:07:03</time_received>
    <statistics>
        <total_issued_ballot_papers>773</total_issued_ballot_papers>
        <total_party_informals>7</total_party_informals>
        <total_candidate_informals>13</total_candidate_informals>
    </statistics>
    <partyvotes>
        <party p_no="5">
            <votes>52</votes>
        </party>
        <party p_no="52">
            <votes>1</votes>
        </party>
        <party p_no="36">
            <votes>2</votes>
        </party>
        <party p_no="49">
            <votes>0</votes>
        </party>
        <party p_no="51">
            <votes>6</votes>
        </party>
        <party p_no="10">
            <votes>39</votes>
        </party>
        <party p_no="13">
            <votes>117</votes>
        </party>
        <party p_no="55">
            <votes>0</votes>
        </party>
        <party p_no="16">
            <votes>482</votes>
        </party>
        <party p_no="34">
            <votes>0</votes>
        </party>
        <party p_no="50">
            <votes>0</votes>
        </party>
        <party p_no="17">
            <votes>39</votes>
        </party>
        <party p_no="54">
            <votes>12</votes>
        </party>
        <party p_no="37">
            <votes>2</votes>
        </party>
        <party p_no="14">
            <votes>4</votes>
        </party>
        <party p_no="24">
            <votes>7</votes>
        </party>
        <party p_no="56">
            <votes>1</votes>
        </party>
    </partyvotes>
    <candidatevotes>
        <candidate c_no="362">
            <votes>25</votes>
        </candidate>
        <candidate c_no="277">
            <votes>42</votes>
        </candidate>
        <candidate c_no="21">
            <votes>3</votes>
        </candidate>
        <candidate c_no="70">
            <votes>546</votes>
        </candidate>
        <candidate c_no="185">
            <votes>17</votes>
        </candidate>
        <candidate c_no="337">
            <votes>125</votes>
        </candidate>
    </candidatevotes>
</votingplace>